BianchengZhiFaMianshiHeSuanfaXinde/README.md
BianchengZhiFaMianshiHeSuanfaXinde/__init__.py
BianchengZhiFaMianshiHeSuanfaXinde/__main__.py
BianchengZhiFaMianshiHeSuanfaXinde/file.epub
BianchengZhiFaMianshiHeSuanfaXinde/index.html
BianchengZhiFaMianshiHeSuanfaXinde/css/__init__.py
BianchengZhiFaMianshiHeSuanfaXinde/css/annotations.css
BianchengZhiFaMianshiHeSuanfaXinde/css/main.css
BianchengZhiFaMianshiHeSuanfaXinde/css/normalize.css
BianchengZhiFaMianshiHeSuanfaXinde/css/popup.css
BianchengZhiFaMianshiHeSuanfaXinde/font/__init__.py
BianchengZhiFaMianshiHeSuanfaXinde/font/fontello.eot
BianchengZhiFaMianshiHeSuanfaXinde/font/fontello.svg
BianchengZhiFaMianshiHeSuanfaXinde/font/fontello.ttf
BianchengZhiFaMianshiHeSuanfaXinde/font/fontello.woff
BianchengZhiFaMianshiHeSuanfaXinde/img/__init__.py
BianchengZhiFaMianshiHeSuanfaXinde/img/annotator-glyph-sprite.png
BianchengZhiFaMianshiHeSuanfaXinde/img/annotator-icon-sprite.png
BianchengZhiFaMianshiHeSuanfaXinde/img/apple-touch-icon.png
BianchengZhiFaMianshiHeSuanfaXinde/img/cancelfullscreen.png
BianchengZhiFaMianshiHeSuanfaXinde/img/close.png
BianchengZhiFaMianshiHeSuanfaXinde/img/fullscreen.png
BianchengZhiFaMianshiHeSuanfaXinde/img/loader.gif
BianchengZhiFaMianshiHeSuanfaXinde/img/menu-icon.png
BianchengZhiFaMianshiHeSuanfaXinde/img/save.png
BianchengZhiFaMianshiHeSuanfaXinde/img/saved.png
BianchengZhiFaMianshiHeSuanfaXinde/img/settings-s.png
BianchengZhiFaMianshiHeSuanfaXinde/img/settings.png
BianchengZhiFaMianshiHeSuanfaXinde/img/star.png
BianchengZhiFaMianshiHeSuanfaXinde/js/__init__.py
BianchengZhiFaMianshiHeSuanfaXinde/js/epub.js
BianchengZhiFaMianshiHeSuanfaXinde/js/epub.min.js
BianchengZhiFaMianshiHeSuanfaXinde/js/epub.min.map
BianchengZhiFaMianshiHeSuanfaXinde/js/hooks.min.js
BianchengZhiFaMianshiHeSuanfaXinde/js/hooks.min.map
BianchengZhiFaMianshiHeSuanfaXinde/js/reader.js
BianchengZhiFaMianshiHeSuanfaXinde/js/reader.js.map
BianchengZhiFaMianshiHeSuanfaXinde/js/reader.min.js
biancheng_zhi_fa_mianshi_he_suanfa_xinde-2024.3.1.0.dist-info/METADATA
biancheng_zhi_fa_mianshi_he_suanfa_xinde-2024.3.1.0.dist-info/WHEEL
biancheng_zhi_fa_mianshi_he_suanfa_xinde-2024.3.1.0.dist-info/entry_points.txt
biancheng_zhi_fa_mianshi_he_suanfa_xinde-2024.3.1.0.dist-info/top_level.txt
biancheng_zhi_fa_mianshi_he_suanfa_xinde-2024.3.1.0.dist-info/RECORD
